fecloudsdkcore/__init__.py
fecloudsdkcore/client.py
fecloudsdkcore/sdk_request.py
fecloudsdkcore/sdk_response.py
fecloudsdkcore/sdk_stream_request.py
fecloudsdkcore/sdk_stream_response.py
fecloudsdkcore/auth/__init__.py
fecloudsdkcore/auth/cache.py
fecloudsdkcore/auth/credentials.py
fecloudsdkcore/auth/internal.py
fecloudsdkcore/auth/provider.py
fecloudsdkcore/exceptions/__init__.py
fecloudsdkcore/exceptions/exception_handler.py
fecloudsdkcore/exceptions/exceptions.py
fecloudsdkcore/http/__init__.py
fecloudsdkcore/http/formdata.py
fecloudsdkcore/http/future_session.py
fecloudsdkcore/http/http_client.py
fecloudsdkcore/http/http_config.py
fecloudsdkcore/http/http_handler.py
fecloudsdkcore/http/primitive_types.py
fecloudsdkcore/http/progress.py
fecloudsdkcore/region/__init__.py
fecloudsdkcore/region/cache.py
fecloudsdkcore/region/provider.py
fecloudsdkcore/region/region.py
fecloudsdkcore/signer/__init__.py
fecloudsdkcore/signer/algorithm.py
fecloudsdkcore/signer/gm.py
fecloudsdkcore/signer/hkdf.py
fecloudsdkcore/signer/signer.py
fecloudsdkcore/utils/__init__.py
fecloudsdkcore/utils/core_utils.py
fecloudsdkcore/utils/filepath_utils.py
fecloudsdkcore/utils/http_utils.py
fecloudsdkcore/utils/six_utils.py
fecloudsdkcore/utils/string_utils.py
fecloudsdkcore/utils/time_utils.py
fecloudsdkcore/utils/xml_utils.py
fecloudsdkcore-0.0.1b0.dist-info/LICENSE
fecloudsdkcore-0.0.1b0.dist-info/METADATA
fecloudsdkcore-0.0.1b0.dist-info/WHEEL
fecloudsdkcore-0.0.1b0.dist-info/top_level.txt
fecloudsdkcore-0.0.1b0.dist-info/RECORD
